argparse_types.py
argparse_types-0.2.0.dist-info/LICENSE
argparse_types-0.2.0.dist-info/METADATA
argparse_types-0.2.0.dist-info/WHEEL
argparse_types-0.2.0.dist-info/top_level.txt
argparse_types-0.2.0.dist-info/RECORD
