Metadata-Version: 2.1
Name: argparse-types
Version: 0.2.0
Summary: addition types to use with argparse
Home-page: https://github.com/tech-chad/argparse_types
Author: Chad Larson
Author-email: techchad2@gmail.com
License: MIT
Platform: UNKNOWN
Classifier: Programming Language :: Python :: 3
Classifier: Programming Language :: Python :: 3.6
Classifier: Programming Language :: Python :: 3.7
Requires-Python: >=3.6.1
